peopledatalabs/__init__.py
peopledatalabs/endpoints/__init__.py
peopledatalabs/endpoints/company.py
peopledatalabs/endpoints/location.py
peopledatalabs/endpoints/person.py
peopledatalabs/endpoints/school.py
peopledatalabs/errors.py
peopledatalabs/logger.py
peopledatalabs/main.py
peopledatalabs/models/__init__.py
peopledatalabs/models/company.py
peopledatalabs/models/location.py
peopledatalabs/models/person.py
peopledatalabs/models/school.py
peopledatalabs/requests.py
peopledatalabs/settings.py
peopledatalabs/utils.py
peopledatalabs-6.4.8.dist-info/METADATA
peopledatalabs-6.4.8.dist-info/WHEEL
peopledatalabs-6.4.8.dist-info/licenses/LICENSE
peopledatalabs-6.4.8.dist-info/RECORD
