Metadata-Version: 2.4
Name: peopledatalabs
Version: 6.4.8
Summary: Official Python client for the People Data Labs API
License: MIT
License-File: LICENSE
Keywords: data enrichment,people data labs,person enrichment,company enrichment,search
Author: People Data Labs
Author-email: hello@peopledatalabs.com
Requires-Python: >=3.8,<4.0
Classifier: Development Status :: 5 - Production/Stable
Classifier: Intended Audience :: Developers
Classifier: License :: OSI Approved :: MIT License
Classifier: Programming Language :: Python :: 3
Classifier: Programming Language :: Python :: 3.8
Classifier: Programming Language :: Python :: 3.9
Classifier: Programming Language :: Python :: 3.10
Classifier: Programming Language :: Python :: 3.11
Classifier: Programming Language :: Python :: 3.12
Classifier: Programming Language :: Python :: 3.13
Classifier: Programming Language :: Python :: 3.14
Classifier: Programming Language :: Python :: Implementation :: PyPy
Classifier: Topic :: Software Development :: Libraries :: Python Modules
Requires-Dist: email-validator (>=1.1,<3.0)
Requires-Dist: pydantic (>=2,<3)
Requires-Dist: requests (>=2,<3)
Project-URL: Bug Tracker, https://github.com/peopledatalabs/peopledatalabs-python/issues
Project-URL: Documentation, https://docs.peopledatalabs.com
Project-URL: Homepage, https://www.peopledatalabs.com
Project-URL: Repository, https://github.com/peopledatalabs/peopledatalabs-python
Project-URL: Source Code, https://github.com/peopledatalabs/peopledatalabs-python
